LICENSE
MANIFEST.in
README.rst
requirements-dev.txt
requirements.txt
setup.py
tox.ini
bin/snakebite
scripts/snakebite-completion.bash
snakebite/__init__.py
snakebite/channel.py
snakebite/client.py
snakebite/commandlineparser.py
snakebite/config.py
snakebite/crc32c.py
snakebite/errors.py
snakebite/formatter.py
snakebite/glob.py
snakebite/kerberos.py
snakebite/logger.py
snakebite/minicluster.py
snakebite/namenode.py
snakebite/platformutils.py
snakebite/rpc_sasl.py
snakebite/service.py
snakebite/version.py
snakebite.egg-info/PKG-INFO
snakebite.egg-info/SOURCES.txt
snakebite.egg-info/dependency_links.txt
snakebite.egg-info/requires.txt
snakebite.egg-info/top_level.txt
snakebite/protobuf/ClientNamenodeProtocol_pb2.py
snakebite/protobuf/IpcConnectionContext_pb2.py
snakebite/protobuf/ProtobufRpcEngine_pb2.py
snakebite/protobuf/RpcHeader_pb2.py
snakebite/protobuf/Security_pb2.py
snakebite/protobuf/__init__.py
snakebite/protobuf/datatransfer_pb2.py
snakebite/protobuf/hdfs_pb2.py