Metadata-Version: 1.1
Name: snakebite
Version: 2.6.1
Summary: Pure Python HDFS client
Home-page: http://github.com/spotify/snakebite
Author: Wouter de Bie
Author-email: wouter@spotify.com
License: Apache License 2.0
Keywords: hadoop,protobuf,hdfs
Platform: UNKNOWN
Classifier: Topic :: Utilities
Classifier: Programming Language :: Python
Classifier: Operating System :: POSIX :: Linux
Classifier: Operating System :: MacOS
Classifier: Topic :: Software Development :: Libraries :: Application Frameworks
Classifier: Environment :: Other Environment
